synthetic_eval/__init__.py
synthetic_eval/evaluation.py
synthetic_eval/metric_MLu.py
synthetic_eval/metric_privacy.py
synthetic_eval/metric_stat.py
synthetic_eval/utility.py
synthetic_eval-0.1.4.dist-info/LICENSE
synthetic_eval-0.1.4.dist-info/METADATA
synthetic_eval-0.1.4.dist-info/WHEEL
synthetic_eval-0.1.4.dist-info/top_level.txt
synthetic_eval-0.1.4.dist-info/RECORD
