Metadata-Version: 2.1
Name: synthetic-eval
Version: 0.1.4
Summary: Package for Evaluation of Synthetic Tabular Data Quality
Home-page: https://github.com/an-seunghwan/synthetic_eval
Author: Seunghwan An
Author-email: dpeltms79@gmail.com
Classifier: Programming Language :: Python :: 3
Requires-Python: >=3.8
License-File: LICENSE
Requires-Dist: backports.tarfile==1.2.0
Requires-Dist: certifi==2024.7.4
Requires-Dist: charset-normalizer==3.3.2
Requires-Dist: docutils==0.21.2
Requires-Dist: filelock==3.15.4
Requires-Dist: fsspec==2024.6.1
Requires-Dist: idna==3.7
Requires-Dist: importlib_metadata==8.2.0
Requires-Dist: jaraco.classes==3.4.0
Requires-Dist: jaraco.context==5.3.0
Requires-Dist: jaraco.functools==4.0.1
Requires-Dist: Jinja2==3.1.4
Requires-Dist: joblib==1.4.2
Requires-Dist: keyring==25.2.1
Requires-Dist: markdown-it-py==3.0.0
Requires-Dist: MarkupSafe==2.1.5
Requires-Dist: mdurl==0.1.2
Requires-Dist: more-itertools==10.3.0
Requires-Dist: mpmath==1.3.0
Requires-Dist: networkx==3.2
Requires-Dist: nh3==0.2.18
Requires-Dist: numpy==1.26.4
Requires-Dist: pandas==2.2.2
Requires-Dist: pip==24.0
Requires-Dist: pkginfo==1.10.0
Requires-Dist: Pygments==2.18.0
Requires-Dist: python-dateutil==2.9.0.post0
Requires-Dist: pytz==2024.1
Requires-Dist: readme_renderer==44.0
Requires-Dist: requests==2.32.3
Requires-Dist: requests-toolbelt==1.0.0
Requires-Dist: rfc3986==2.0.0
Requires-Dist: rich==13.7.1
Requires-Dist: scikit-learn==1.5.1
Requires-Dist: scipy==1.13.0
Requires-Dist: setuptools==69.5.1
Requires-Dist: six==1.16.0
Requires-Dist: sympy==1.13.1
Requires-Dist: threadpoolctl==3.5.0
Requires-Dist: torch==2.2.2
Requires-Dist: tqdm==4.66.4
Requires-Dist: twine==5.1.1
Requires-Dist: typing_extensions==4.12.2
Requires-Dist: tzdata==2024.1
Requires-Dist: urllib3==2.2.2
Requires-Dist: wheel==0.43.0
Requires-Dist: zipp==3.19.2
